pyhilo/__init__.py
pyhilo/api.py
pyhilo/const.py
pyhilo/device/__init__.py
pyhilo/device/climate.py
pyhilo/device/graphql_value_mapper.py
pyhilo/device/light.py
pyhilo/device/sensor.py
pyhilo/device/switch.py
pyhilo/devices.py
pyhilo/event.py
pyhilo/exceptions.py
pyhilo/graphql.py
pyhilo/oauth2helper.py
pyhilo/util/__init__.py
pyhilo/util/state.py
pyhilo/websocket.py
python_hilo-2026.1.2.dist-info/METADATA
python_hilo-2026.1.2.dist-info/WHEEL
python_hilo-2026.1.2.dist-info/licenses/LICENSE
python_hilo-2026.1.2.dist-info/RECORD
