Metadata-Version: 2.4
Name: python-hilo
Version: 2026.1.2
Summary: A Python3, async interface to the Hilo API
License: MIT
License-File: LICENSE
Author: David Vallee Delisle
Author-email: me@dvd.dev
Maintainer: David Vallee Delisle
Maintainer-email: me@dvd.dev
Requires-Python: >=3.9.0,<4.0.0
Classifier: Framework :: aiohttp
Classifier: License :: OSI Approved :: MIT License
Classifier: Programming Language :: Python
Classifier: Programming Language :: Python :: 3
Classifier: Programming Language :: Python :: 3.9
Classifier: Programming Language :: Python :: 3.10
Classifier: Programming Language :: Python :: 3.11
Classifier: Programming Language :: Python :: 3.12
Classifier: Programming Language :: Python :: 3.13
Classifier: Programming Language :: Python :: 3.14
Classifier: Programming Language :: Python :: Implementation :: CPython
Classifier: Programming Language :: Python :: Implementation :: PyPy
Classifier: Topic :: Home Automation
Requires-Dist: aiofiles (>=23.2.1)
Requires-Dist: aiohttp (>=3.8.0)
Requires-Dist: aiosignal (>=1.2.0)
Requires-Dist: async-timeout (>=4.0.0)
Requires-Dist: attrs (>=21.2.0)
Requires-Dist: backoff (>=1.11.1)
Requires-Dist: gql (>=3.5.2,<5.0.0)
Requires-Dist: python-dateutil (>=2.8.2)
Requires-Dist: pyyaml (>=6.0.2,<7.0.0)
Requires-Dist: voluptuous (>=0.13.1)
Requires-Dist: websockets (>=8.1,<16.0)
Project-URL: Repository, https://github.com/dvd-dev/python-hilo
